django_dto_attrs/__init__.py
django_dto_attrs-0.1.0.dev0.dist-info/METADATA
django_dto_attrs-0.1.0.dev0.dist-info/WHEEL
django_dto_attrs-0.1.0.dev0.dist-info/licenses/LICENSE
django_dto_attrs-0.1.0.dev0.dist-info/RECORD
