Metadata-Version: 2.3
Name: django-dto-attrs
Version: 0.1.0.dev0
Summary: High performance DTOs with Django ORM integration and optional validation.
Project-URL: Repository, https://github.com/flango-dev/django-dto-attrs
Project-URL: Documentation, https://github.com/flango-dev/django-dto-attrs/blob/main/README.md
Project-URL: Changelog, https://github.com/flango-dev/django-dto-attrs/blob/main/CHANGELOG.md
Author-email: Florian Kromer <kromer-florian@protonmail.com>
License: MIT License
License-File: LICENSE
Classifier: Development Status :: 1 - Planning
Classifier: Framework :: Django
Classifier: Intended Audience :: Developers
Classifier: License :: OSI Approved :: MIT License
Classifier: Operating System :: OS Independent
Classifier: Programming Language :: Python
Classifier: Programming Language :: Python :: 3.12
Requires-Python: >=3.12
Requires-Dist: attrs>=23.2.0
Requires-Dist: cattrs>=23.2.3
